bin/__init__.py
i_love_sam/__init__.py
i_love_sam/i_love.py
i_love_sam-70.data/scripts/i_love_sam
i_love_sam-70.dist-info/METADATA
i_love_sam-70.dist-info/RECORD
i_love_sam-70.dist-info/WHEEL
i_love_sam-70.dist-info/top_level.txt
