Metadata-Version: 2.1
Name: i-love-sam
Version: 70
Summary: I love sam
Home-page: UNKNOWN
Author: nilloc
License: MIT License
Platform: UNKNOWN
Classifier: Programming Language :: Python :: 3
Classifier: License :: OSI Approved :: MIT License
Classifier: Operating System :: OS Independent
